api42lib/IntraAPIClient.py
api42lib/Token.py
api42lib/__init__.py
api42lib/utils.py
api42lib-0.1.10.dist-info/METADATA
api42lib-0.1.10.dist-info/WHEEL
api42lib-0.1.10.dist-info/top_level.txt
api42lib-0.1.10.dist-info/RECORD
