Metadata-Version: 2.4
Name: api42lib
Version: 0.1.10
Summary: A Python library for interacting with 42.fr API (v2 and v3). Maintained by 42 Berlin.
Author-email: pruiz-ca <pruiz-ca@student.42madrid.com>
License: MIT
Project-URL: Homepage, https://github.com/42Berlin/api42lib
Project-URL: Repository, https://github.com/42Berlin/api42lib
Keywords: api42lib,42,api,42api,ft,ft-api,42school,42-school,42-school-api,42-api,42-lib,42-library
Classifier: Intended Audience :: Developers
Classifier: Topic :: Software Development :: Libraries :: Python Modules
Classifier: Programming Language :: Python :: 3
Classifier: License :: OSI Approved :: MIT License
Classifier: Operating System :: OS Independent
Requires-Python: >=3.6
Requires-Dist: PyYAML<7.0,>=6.0
Requires-Dist: requests<3.0,>=2.25
Requires-Dist: Pygments<3.0,>=2.9
Requires-Dist: tqdm<5.0,>=4.56
Requires-Dist: urllib3<2.0,>=1.26
Requires-Dist: colorlog<7.0,>=6.8.2
